odkconvert/CSVDump.py
odkconvert/ODKDump.py
odkconvert/ODKForm.py
odkconvert/ODKInstance.py
odkconvert/OdkCentral.py
odkconvert/__init__.py
odkconvert/__version__.py
odkconvert/basemapper.py
odkconvert/convert.py
odkconvert/data_models/Impact Areas - Data Models V1.1.xlsx
odkconvert/data_models/buildings.yaml
odkconvert/data_models/education.yaml
odkconvert/data_models/emergency.yaml
odkconvert/data_models/healthcare.yaml
odkconvert/data_models/landuse.yaml
odkconvert/data_models/models.yaml
odkconvert/data_models/natural.yaml
odkconvert/data_models/place.yaml
odkconvert/data_models/religious.yaml
odkconvert/data_models/toilets.yaml
odkconvert/data_models/validate.py
odkconvert/data_models/waste.yaml
odkconvert/data_models/waterpoints.yaml
odkconvert/data_models/waterways.yaml
odkconvert/filter.yaml
odkconvert/filter_data.py
odkconvert/make_data_extract.py
odkconvert/odk2csv.py
odkconvert/odk_client.py
odkconvert/odk_merge.py
odkconvert/osmfile.py
odkconvert/sqlite.py
odkconvert/xforms.yaml
odkconvert/xlsforms/Makefile
odkconvert/xlsforms/__init__.py
odkconvert/xlsforms/buildings.xls
odkconvert/xlsforms/cemeteries.xls
odkconvert/xlsforms/education.xls
odkconvert/xlsforms/healthcare.xls
odkconvert/xlsforms/landuse.xls
odkconvert/xlsforms/lib/amenities.csv
odkconvert/xlsforms/lib/buildings.csv
odkconvert/xlsforms/lib/municipality.csv
odkconvert/xlsforms/lib/opening_hours.csv
odkconvert/xlsforms/lib/operational_status.csv
odkconvert/xlsforms/lib/provider.csv
odkconvert/xlsforms/lib/towns.csv
odkconvert/xlsforms/lib/waste.csv
odkconvert/xlsforms/municipality.csv
odkconvert/xlsforms/natural.xls
odkconvert/xlsforms/place.xls
odkconvert/xlsforms/religious.xls
odkconvert/xlsforms/school.xls
odkconvert/xlsforms/solidwaste.xlsx
odkconvert/xlsforms/toilets.xls
odkconvert/xlsforms/towns.csv
odkconvert/xlsforms/transportation.xls
odkconvert/xlsforms/waste.xls
odkconvert/xlsforms/waste_collection.xlsx
odkconvert/xlsforms/waterpoints.xls
odkconvert/xlsforms/waterways.xls
ODKConvert-0.1.1.dist-info/WHEEL
ODKConvert-0.1.1.dist-info/METADATA
ODKConvert-0.1.1.dist-info/licenses/LICENSE.md
ODKConvert-0.1.1.dist-info/RECORD
