Metadata-Version: 2.1
Name: ODKConvert
Version: 0.1.1
Summary: Convert CSV files from ODK Central to OSM format.
License: GPL-3.0-only
Keywords: fmtm,odk,hot,openstreetmap,opendatakit
Author-email: Rob Savoye <rob.savoye@hotosm.org>
Requires-Python: >=3.9
Classifier: Programming Language :: Python :: 3
Classifier: Programming Language :: Python :: 3.9
Classifier: Topic :: Scientific/Engineering :: GIS
Classifier: Topic :: Utilities
Requires-Dist: OSMPythonTools>=0.3.5
Requires-Dist: PyYAML>=6.0
Requires-Dist: codetiming>=1.4.0
Requires-Dist: epdb>=0.15.1
Requires-Dist: geodex>=0.1.2
Requires-Dist: geojson>=2.5.0
Requires-Dist: progress>=1.6
Requires-Dist: pymbtiles>=0.5.0
Requires-Dist: qrcode>=7.4.2
Requires-Dist: requests>=2.28.2
Requires-Dist: segno>=1.5.2
Requires-Dist: shapely>=1.8.5
Requires-Dist: xmltodict>=0.13.0
Project-URL: documentation, https://github.com/hotosm/odkconvert/wiki
Project-URL: homepage, https://github.com/hotosm/odkconvert/wiki
Project-URL: repository, https://github.com/hotosm/odkconvert
